tulips/__init__.py
tulips/__main__.py
tulips/resource/__init__.py
tulips/resource/certificate.py
tulips/resource/configmap.py
tulips/resource/cronjob.py
tulips/resource/deployment.py
tulips/resource/hpa.py
tulips/resource/ingress.py
tulips/resource/issuer.py
tulips/resource/job.py
tulips/resource/networkpolicy.py
tulips/resource/persistentvolumeclaim.py
tulips/resource/resourcequota.py
tulips/resource/secret.py
tulips/resource/service.py
tulips/resource/statefullset.py
tulips/tulip.py
tulips-1.5.10.dist-info/WHEEL
tulips-1.5.10.dist-info/METADATA
tulips-1.5.10.dist-info/RECORD
