Metadata-Version: 2.1
Name: tulips
Version: 1.5.10
Summary: Wrapper around kubernetes-clients/python
Home-page: https://github.com/dz0ny/tulips
License: MIT
Author: Janez Troha
Author-email: dz0ny@ubuntu.si
Requires-Python: >=3.6,<4
Classifier: License :: OSI Approved :: MIT License
Classifier: Programming Language :: Python :: 3
Classifier: Programming Language :: Python :: 3.6
Classifier: Programming Language :: Python :: 3.7
Classifier: Programming Language :: Python :: 3.8
Classifier: Programming Language :: Python :: 3.9
Requires-Dist: click (>=6.7)
Requires-Dist: kubernetes (==19.15.0)
Requires-Dist: passlib (>=1.7,<2.0)
Requires-Dist: regex (==2020.10.11)
Requires-Dist: ruamel.yaml (>=0.15.89)
Requires-Dist: structlog
Project-URL: Repository, https://github.com/dz0ny/tulips
